f1_23_telemetry/__init__.py
f1_23_telemetry/appendices.py
f1_23_telemetry/listener.py
f1_23_telemetry/main.py
f1_23_telemetry/packets.py
f1_23_telemetry-0.1.4.dist-info/LICENSE
f1_23_telemetry-0.1.4.dist-info/METADATA
f1_23_telemetry-0.1.4.dist-info/WHEEL
f1_23_telemetry-0.1.4.dist-info/RECORD
