Metadata-Version: 2.1
Name: f1-23-telemetry
Version: 0.1.4
Summary: 
License: MIT
Author: Chris Hannam
Author-email: ch@chrishannam.co.uk
Requires-Python: >=3.8,<4.0
Classifier: License :: OSI Approved :: MIT License
Classifier: Programming Language :: Python :: 3
Classifier: Programming Language :: Python :: 3.8
Classifier: Programming Language :: Python :: 3.9
Classifier: Programming Language :: Python :: 3.10
Classifier: Programming Language :: Python :: 3.11
